streamlit_kanban/__init__.py
streamlit_kanban/example.py
streamlit_kanban/frontend/build/asset-manifest.json
streamlit_kanban/frontend/build/bootstrap.min.css
streamlit_kanban/frontend/build/index.html
streamlit_kanban/frontend/build/static/js/main.aae672ad.js
streamlit_kanban/frontend/build/static/js/main.aae672ad.js.LICENSE.txt
streamlit_kanban/frontend/build/static/js/main.aae672ad.js.map
streamlit_kanban-1.0.0.dist-info/LICENSE
streamlit_kanban-1.0.0.dist-info/METADATA
streamlit_kanban-1.0.0.dist-info/WHEEL
streamlit_kanban-1.0.0.dist-info/top_level.txt
streamlit_kanban-1.0.0.dist-info/RECORD
