Metadata-Version: 2.1
Name: streamlit-kanban
Version: 1.0.0
Summary: This streamlit component uses react beautiful dnd to provide you a kanban structure where you can create dinamically the kanban columns and cards with also dynamic fields
Home-page: 
Author: Andre Scudiere
Author-email: andrescudiere@gmail.com
Requires-Python: >=3.12
License-File: LICENSE
Requires-Dist: streamlit>=1.4
Provides-Extra: devel
Requires-Dist: wheel; extra == "devel"
Requires-Dist: pytest==7.4.0; extra == "devel"
Requires-Dist: playwright==1.48.0; extra == "devel"
Requires-Dist: requests==2.31.0; extra == "devel"
Requires-Dist: pytest-playwright-snapshot==1.0; extra == "devel"
Requires-Dist: pytest-rerunfailures==12.0; extra == "devel"
